torrent_crawler/__init__.py
torrent_crawler/color.py
torrent_crawler/constants.py
torrent_crawler/crawler.py
torrent_crawler/helper.py
torrent_crawler/models.py
torrent_crawler/print.py
torrent_crawler/search.py
torrent_crawler/subtitle.py
search_torrent-1.4.3.dist-info/LICENSE
search_torrent-1.4.3.dist-info/METADATA
search_torrent-1.4.3.dist-info/WHEEL
search_torrent-1.4.3.dist-info/entry_points.txt
search_torrent-1.4.3.dist-info/top_level.txt
search_torrent-1.4.3.dist-info/RECORD
