Metadata-Version: 2.1
Name: search-torrent
Version: 1.4.3
Summary: Search for torrents using command line
Home-page: http://github.com/rajat19/torrent-crawler
Author: Rajat Srivastava
Author-email: rajatsri94@gmail.com
License: UNKNOWN
Download-URL: https://github.com/rajat19/torrent-crawler/releases
Keywords: pip,torrent,crawler
Platform: UNKNOWN
Classifier: Intended Audience :: Developers
Classifier: Programming Language :: Python :: 3
Classifier: License :: OSI Approved :: MIT License
Classifier: Operating System :: OS Independent
